{
  "sections": {
    "slideshow": {
      "type": "slideshow",
      "blocks": {
        "slideshow-0": {
          "type": "image",
          "settings": {
            "top_subheading": "",
            "title": "Two line\ntitle slide.",
            "title_size": 60,
            "subheading": "And optional subtext",
            "link": "shopify:\/\/collections",
            "link_text": "Shop this",
            "link_2": "shopify:\/\/collections\/all",
            "link_text_2": "Shop all",
            "color_accent": "#ffffff",
            "text_align": "vertical-center horizontal-center",
            "overlay_opacity": 20,
            "focal_point": "center center"
          }
        }
      },
      "block_order": [
        "slideshow-0"
      ],
      "settings": {
        "section_height": "100vh",
        "mobile_height": "100vh",
        "parallax": true,
        "style": "dots",
        "autoplay": true,
        "autoplay_speed": 7
      }
    },
    "featured-collections": {
      "type": "featured-collections",
      "blocks": {
        "featured-collections-0": {
          "type": "collection",
          "settings": {
            "collection": "lights-lighting",
            "title": "",
            "focal_point": "center center"
          }
        },
        "featured-collections-1": {
          "type": "collection",
          "settings": {
            "collection": "personal-organizers",
            "title": "",
            "focal_point": "center center"
          }
        },
        "featured-collections-3": {
          "type": "collection",
          "settings": {
            "collection": "baby-and-toddler-toys",
            "title": "",
            "focal_point": "center center"
          }
        },
        "c2c4fd4f-b575-4979-8cc0-c9e1927ecd4d": {
          "type": "collection",
          "settings": {
            "collection": "bags-handbags",
            "title": "",
            "focal_point": "center center"
          }
        },
        "6f836d51-f9e3-4aab-8849-3b04fa91458b": {
          "type": "collection",
          "settings": {
            "collection": "wallets",
            "title": "",
            "focal_point": "center center"
          }
        },
        "93e7e771-7c75-4213-b3b6-eac4b1f0ba6c": {
          "type": "collection",
          "settings": {
            "collection": "kitchen-dining-bar",
            "title": "",
            "focal_point": "center center"
          }
        },
        "7cbfa37e-c751-4298-b0ec-7803bfa24818": {
          "type": "collection",
          "settings": {
            "collection": "miscellaneous",
            "title": "",
            "focal_point": "center center"
          }
        },
        "64462a33-7e1a-4f0f-b859-fc9ffd36d342": {
          "type": "collection",
          "settings": {
            "collection": "diy-craft-accessories",
            "title": "",
            "focal_point": "center center"
          }
        }
      },
      "block_order": [
        "featured-collections-0",
        "featured-collections-1",
        "featured-collections-3",
        "c2c4fd4f-b575-4979-8cc0-c9e1927ecd4d",
        "6f836d51-f9e3-4aab-8849-3b04fa91458b",
        "93e7e771-7c75-4213-b3b6-eac4b1f0ba6c",
        "7cbfa37e-c751-4298-b0ec-7803bfa24818",
        "64462a33-7e1a-4f0f-b859-fc9ffd36d342"
      ],
      "settings": {
        "title": "Shop by category",
        "divider": false,
        "per_row": 4,
        "enable_gutter": true
      }
    },
    "promo-grid": {
      "type": "promo-grid",
      "blocks": {
        "promo-0": {
          "type": "advanced",
          "settings": {
            "subheading": "Limited time",
            "heading": "Limited Time",
            "textarea": "new des",
            "cta_text1": "Shop This",
            "cta_link1": "shopify:\/\/collections\/all",
            "cta_text2": "",
            "cta_link2": "",
            "video_url": "",
            "width": "50",
            "height": 500,
            "text_size": 80,
            "text_align": "vertical-top horizontal-right",
            "focal_point": "center",
            "color_accent": "rgba(0,0,0,0)",
            "boxed": true,
            "framed": true
          }
        },
        "promo-1": {
          "type": "advanced",
          "settings": {
            "subheading": "Limited time",
            "heading": "Limited time",
            "textarea": "Include the smaller details of your.",
            "cta_text1": "Shop This",
            "cta_link1": "shopify:\/\/collections\/all",
            "cta_text2": "",
            "cta_link2": "",
            "video_url": "",
            "width": "50",
            "height": 500,
            "text_size": 80,
            "text_align": "vertical-top horizontal-left",
            "focal_point": "80% 50%",
            "color_accent": "rgba(0,0,0,0)",
            "boxed": true,
            "framed": true
          }
        }
      },
      "block_order": [
        "promo-0",
        "promo-1"
      ],
      "settings": {
        "full_width": true,
        "gutter_size": 20,
        "space_above": false,
        "space_below": false
      }
    },
    "featured-collection": {
      "type": "featured-collection",
      "settings": {
        "title": "Container & Storage",
        "home_featured_products": "containers-storage",
        "per_row": 4,
        "rows": 1,
        "mobile_scrollable": false,
        "view_all": false,
        "divider": false
      }
    },
    "background-image-text": {
      "type": "background-image-text",
      "settings": {
        "subtitle": "Impressive",
        "title": "Large image with text box",
        "text": "<p>Pair large text with a full-width image to draw attention to an important detail of your brand or product line.<\/p>",
        "button_label": "",
        "button_link": "shopify:\/\/collections\/all",
        "focal_point": "80% 0",
        "layout": "left",
        "height": 750,
        "framed": false,
        "parallax": false
      }
    },
    "11980fc9-dc95-4f08-9d7e-edfe789a5c79": {
      "type": "featured-collection",
      "settings": {
        "title": "Bar Essentials",
        "home_featured_products": "kitchen-dining-bar",
        "per_row": 4,
        "rows": 1,
        "mobile_scrollable": false,
        "view_all": false,
        "divider": false
      }
    }
  },
  "order": [
    "slideshow",
    "featured-collections",
    "promo-grid",
    "featured-collection",
    "background-image-text",
    "11980fc9-dc95-4f08-9d7e-edfe789a5c79"
  ]
}
